hw_midterm_exam/__init__.py
hw_midterm_exam/hw_midterm_exam.py
hw_midterm_exam-0.0.2.dist-info/LICENSE
hw_midterm_exam-0.0.2.dist-info/METADATA
hw_midterm_exam-0.0.2.dist-info/WHEEL
hw_midterm_exam-0.0.2.dist-info/top_level.txt
hw_midterm_exam-0.0.2.dist-info/RECORD
